bip32key/__init__.py
bip32key-0.1.2.dist-info/METADATA
bip32key-0.1.2.dist-info/RECORD
bip32key-0.1.2.dist-info/WHEEL
bip32key-0.1.2.dist-info/top_level.txt
