Metadata-Version: 2.1
Name: bip32key
Version: 0.1.2
Summary: The implementation of Hierarchical Deterministic (HD) wallets generator for Ethereum blockchain
Home-page: https://github.com/mehetett/bip32key
Author: Meheret Tesfaye
Author-email: meherett@zoho.com
License: MIT
Platform: UNKNOWN
Classifier: Development Status :: 3 - Alpha
Classifier: License :: OSI Approved :: MIT License
Classifier: Programming Language :: Python :: 3.5
Classifier: Programming Language :: Python :: 3.6
Classifier: Programming Language :: Python :: 3.7
Requires-Python: >=3.5,<3.7
Requires-Dist: ecdsa (==0.13)
Requires-Dist: two1 (==3.10.9)
Requires-Dist: base58 (==0.2.2)
Requires-Dist: pysha3 (==1.0.2)
Requires-Dist: mnemonic (==0.13)
Requires-Dist: eth-keyfile (==0.5.1)
